Tool.py
sztestlib/__init__.py
sztestlib/szlibone.py
sztestlib-1.0.0.dist-info/DESCRIPTION.rst
sztestlib-1.0.0.dist-info/METADATA
sztestlib-1.0.0.dist-info/RECORD
sztestlib-1.0.0.dist-info/WHEEL
sztestlib-1.0.0.dist-info/metadata.json
sztestlib-1.0.0.dist-info/top_level.txt
